{"5zgc3O+FpgvIXI8dH3n/Dg==":"slide1-1600x900.jpg","Tn1zTb8iTN794M5b7lrJ7Q==":"slide1-1024x576.jpg","kiDcxgemPbv8kScNnInw4g==":"slide2-1-1024x576.jpg","msdQ4Bk3llqe0M24qvQxmg==":"mbr-720x1080.jpg","R4h2a+i1dmXH+iW8J+j4iw==":"1-1024x576.png","AI7IqzVz2EW6SyshuT3jqA==":"1-1024x576.jpg","mOhyPfMWO0ZLlq63y1znJg==":"2-1024x576.png","FELRd3sbT/siIkaI6X4FWA==":"2-1024x552.jpg","GlX0nRLuQvFSuSZAtzEn8w==":"3-1024x576.png","PmZtdyxm/Xp9n0NNjz0Jlw==":"3-1024x576.jpg","IB1IrEmWcAqHCFGzxMA4wQ==":"4-1024x576.png","o2H+VO4jb2BG90h5gC25mQ==":"4-1024x576.jpg","sNMw3iCxiESnkkY8wt3/yg==":"est%202012-1024x576.png","+Cna64A2b9lAF7Yuf4Mykw==":"est%202012-1024x576.jpg","hKFTu86qo49xLSOvsK+9hQ==":"est%202012-85x47.png","47bBZ2U5fPtJhQzAQbE+aA==":"herbal%20zamzam%20id%20logo-863x1038.png","69HVn1XpitJWTm6ZP807pw==":"est%202012-1024x576.jpg","MPH6gVhO0Dr9grMhsVCeig==":"est%202012-1024x576.jpg","noekO/TLjZjTOPuQHK86LQ==":"1-1-85x47.png","0pamvszswFDBPwy6jWAcZw==":"3-1-85x47.png","QKj7L7HNcdZ17CjvtowB3Q==":"3-1-1024x576.jpg","/Xe1bhpF9Wicu6xZbv3ySQ==":"3-2-85x47.png","GLUCx6HX7KZEayE7xewvVg==":"untitled%20design%20(1)-444x444.jpg","2uqgGPK8yW/cCeKBIxBAhQ==":"untitled%20design%20(2)-444x444.jpg","D/Gf52Bag8V2l+I+rI0SlA==":"untitled%20design-444x444.jpg"}